app/__init__.py
app/asgi.py
app/celery.py
app/logging.py
app/urls.py
app/wsgi.py
app/settings/__init__.py
app/settings/base.py
app/settings/dev.py
app/settings/github_action.py
app/settings/test.py
docs/__init__.py
docs/src/_implied_triggers.md
docs/src/about.md
docs/src/actions.md
docs/src/conditions.md
docs/src/index.md
docs/src/triggers.md
docs/src/variables.md
docs/src/img/android-chrome-192x192.png
docs/src/img/android-chrome-512x512.png
docs/src/img/apple-touch-icon.png
docs/src/img/favicon-16x16.png
docs/src/img/favicon-32x32.png
docs/src/img/favicon.ico
docs/src/img/site.webmanifest
docs/theme/footer.html
sleuthpr/__init__.py
sleuthpr/admin.py
sleuthpr/apps.py
sleuthpr/lock.py
sleuthpr/models.py
sleuthpr/registry.py
sleuthpr/sleuthpr.py
sleuthpr/triggers.py
sleuthpr/urls.py
sleuthpr/util.py
sleuthpr/variables.py
sleuthpr/views.py
sleuthpr/actions/__init__.py
sleuthpr/actions/add_label.py
sleuthpr/actions/merge.py
sleuthpr/actions/update.py
sleuthpr/management/__init__.py
sleuthpr/management/commands/__init__.py
sleuthpr/management/commands/on_github_action.py
sleuthpr/migrations/0001_initial.py
sleuthpr/migrations/0002_auto_20200930_1926.py
sleuthpr/migrations/0003_auto_20200930_2010.py
sleuthpr/migrations/0004_repositorybranch.py
sleuthpr/migrations/0005_pullrequest_base_sha.py
sleuthpr/migrations/0006_repositorycommit_repositorycommitparent.py
sleuthpr/migrations/0007_auto_20201001_1832.py
sleuthpr/migrations/0008_auto_20201001_2012.py
sleuthpr/migrations/0009_auto_20201007_2015.py
sleuthpr/migrations/0010_delete_conditioncheckrun.py
sleuthpr/migrations/0011_trigger_description.py
sleuthpr/migrations/0012_pullrequest_conflict.py
sleuthpr/migrations/0013_auto_20201009_1607.py
sleuthpr/migrations/0014_auto_20201009_2319.py
sleuthpr/migrations/0015_actionresult.py
sleuthpr/migrations/0016_auto_20201010_0654.py
sleuthpr/migrations/0017_auto_20201026_2137.py
sleuthpr/migrations/__init__.py
sleuthpr/services/__init__.py
sleuthpr/services/branches.py
sleuth_pr-0.0.22.dist-info/LICENSE
sleuth_pr-0.0.22.dist-info/METADATA
sleuth_pr-0.0.22.dist-info/WHEEL
sleuth_pr-0.0.22.dist-info/top_level.txt
sleuth_pr-0.0.22.dist-info/RECORD
