Metadata-Version: 2.1
Name: sleuth-pr
Version: 0.0.22
Summary: Pull request automation Django app
Home-page: https://github.com/sleuth-io/sleuth-pr
Author: Don Brown
Author-email: don@sleuth.io
Maintainer: Don Brown
Maintainer-email: don@sleuth.io
License: APLv2 License
Keywords: pull request,automation,bot
Platform: UNKNOWN
Classifier: Development Status :: 3 - Alpha
Classifier: License :: OSI Approved :: Apache Software License
Classifier: Topic :: Software Development
Classifier: Programming Language :: Python :: 3.8
Requires-Python: >=3.8
Requires-Dist: Django (>=3.0.0)
Requires-Dist: celery (>=5.0.0)
Requires-Dist: marshmallow (>=3.8.0)
Requires-Dist: PyGithub (>=1.53)
Requires-Dist: PyJWT (>=1.7.1)
Requires-Dist: requests (>=2.24.0)
Requires-Dist: strictyaml (>=1.0.0)
Requires-Dist: pyparsing (>=2.4.7)
Requires-Dist: cryptography (>=3.1)
Requires-Dist: basictracer (>=3.1.0)
Requires-Dist: opentracing-instrumentation (>=3.2.1)
Requires-Dist: django-opentracing (>=1.1.0)
Requires-Dist: redlock (>=1.2.0)
Provides-Extra: dev
Requires-Dist: pytest ; extra == 'dev'
Requires-Dist: pytest-django ; extra == 'dev'
Requires-Dist: flake8 ; extra == 'dev'
Requires-Dist: pylint ; extra == 'dev'
Requires-Dist: black ; extra == 'dev'
Requires-Dist: reorder-python-imports ; extra == 'dev'
Requires-Dist: factory-boy ; extra == 'dev'
Requires-Dist: mkdocs (>=1.1) ; extra == 'dev'
Requires-Dist: mkdocs-macros-plugin ; extra == 'dev'
Provides-Extra: doc
Requires-Dist: sphinx ; extra == 'doc'
Requires-Dist: sphinx-rtd-theme ; extra == 'doc'
Provides-Extra: prod
Requires-Dist: google-re2 (==0.0.7) ; extra == 'prod'
Provides-Extra: test
Requires-Dist: pytest ; extra == 'test'
